{"cameraMode":{"drawMode":0,"name":"Shaded","section":"Shading Mode"},"sceneLighting":false,"audioPlay":false,"sceneViewState":{"m_AlwaysRefresh":false,"showFog":true,"showSkybox":false,"showFlares":true,"showImageEffects":true,"showParticleSystems":true,"showVisualEffectGraphs":true,"m_FxEnabled":true},"in2DMode":false,"pivot":{"x":7.558609485626221,"y":0.1363561600446701,"z":1.1290944814682007},"rotation":{"x":0.05158340930938721,"y":0.6467386484146118,"z":-0.04394672438502312,"w":0.7599175572395325},"size":5.050010681152344,"orthographic":false}